pyams_i18n/__init__.py
pyams_i18n/attr.py
pyams_i18n/content.py
pyams_i18n/include.py
pyams_i18n/interfaces.py
pyams_i18n/language.py
pyams_i18n/negotiator.py
pyams_i18n/schema.py
pyams_i18n/tales.py
pyams_i18n/vocabulary.py
pyams_i18n/doctests/README.rst
pyams_i18n/generations/__init__.py
pyams_i18n/locales/pyams_i18n.pot
pyams_i18n/locales/fr/LC_MESSAGES/pyams_i18n.mo
pyams_i18n/locales/fr/LC_MESSAGES/pyams_i18n.po
pyams_i18n/tests/__init__.py
pyams_i18n/tests/test_utilsdocs.py
pyams_i18n/tests/test_utilsdocstrings.py
pyams_i18n-2.1.0.dist-info/LICENSE
pyams_i18n-2.1.0.dist-info/METADATA
pyams_i18n-2.1.0.dist-info/WHEEL
pyams_i18n-2.1.0.dist-info/namespace_packages.txt
pyams_i18n-2.1.0.dist-info/top_level.txt
pyams_i18n-2.1.0.dist-info/RECORD
