Metadata-Version: 2.1
Name: pyams-i18n
Version: 2.1.0
Summary: PyAMS content internationalization support
Home-page: https://pyams.readthedocs.io
Author: Thierry Florac
Author-email: tflorac@ulthar.net
License: ZPL
Keywords: Pyramid PyAMS
Classifier: License :: OSI Approved :: Zope Public License
Classifier: Development Status :: 4 - Beta
Classifier: Programming Language :: Python
Classifier: Framework :: Pyramid
Classifier: Topic :: Software Development :: Libraries :: Python Modules
License-File: LICENSE
Requires-Dist: setuptools
Requires-Dist: chameleon
Requires-Dist: persistent
Requires-Dist: pyams-site
Requires-Dist: pyams-utils
Requires-Dist: pyramid >=2.0.0
Requires-Dist: zope.container
Requires-Dist: zope.i18n
Requires-Dist: zope.interface
Requires-Dist: zope.schema
Requires-Dist: zope.traversing
Provides-Extra: test
Requires-Dist: pyramid-zodbconn ; extra == 'test'
Requires-Dist: pyams-template ; extra == 'test'
